CHANGES.rst
MANIFEST.in
README.rst
requirements.txt
setup.py
sc_gitlab_webhook.egg-info/PKG-INFO
sc_gitlab_webhook.egg-info/SOURCES.txt
sc_gitlab_webhook.egg-info/dependency_links.txt
sc_gitlab_webhook.egg-info/entry_points.txt
sc_gitlab_webhook.egg-info/requires.txt
sc_gitlab_webhook.egg-info/top_level.txt
webhook/__init__.py
webhook/exceptions.py
webhook/handlers.py
webhook/main.py
webhook/producer.py
webhook/utils.py
webhook/views.py
webhook/configs/__init__.py
webhook/configs/default.py
webhook/tests/__init__.py
webhook/tests/handler/__init__.py
webhook/tests/handler/handler_test.py
webhook/tests/rocketmq/__init__.py
webhook/tests/rocketmq/consumer_test.py
webhook/tests/rocketmq/producer_test.py
webhook/tests/sample_config/default.yml