Metadata-Version: 1.2
Name: sc-gitlab-webhook
Version: 0.0.7
Summary: A simple Gitlab WebHook
Home-page: https://github.com/Scott-Lau/sc-gitlab-webhook
Author: Scott Lau
Author-email: exceedego@126.com
License: MIT
Keywords: Git Gitlab Python WebHook
Platform: POSIX
Classifier: Programming Language :: Python :: 3
Classifier: Programming Language :: Python :: 3.6
Classifier: Programming Language :: Python :: 3.7
Classifier: Programming Language :: Python :: 3.8
Classifier: Programming Language :: Python :: 3.9
Classifier: License :: OSI Approved :: MIT License
Classifier: Operating System :: OS Independent
Classifier: Topic :: Software Development
Classifier: Topic :: Utilities
Requires-Python: >=3.6
